.travis.yml
CHANGES.txt
COPYRIGHT.txt
LICENSE.txt
MANIFEST.in
bootstrap.py
buildout.cfg
setup.py
tox.ini
src/zope/__init__.py
src/zope.fanstatic.egg-info/PKG-INFO
src/zope.fanstatic.egg-info/SOURCES.txt
src/zope.fanstatic.egg-info/dependency_links.txt
src/zope.fanstatic.egg-info/namespace_packages.txt
src/zope.fanstatic.egg-info/not-zip-safe
src/zope.fanstatic.egg-info/requires.txt
src/zope.fanstatic.egg-info/top_level.txt
src/zope/fanstatic/README.txt
src/zope/fanstatic/__init__.py
src/zope/fanstatic/configure.zcml
src/zope/fanstatic/interfaces.py
src/zope/fanstatic/meta.zcml
src/zope/fanstatic/testing.py
src/zope/fanstatic/zcml.py
src/zope/fanstatic/zopesupport.py
src/zope/fanstatic/tests/__init__.py
src/zope/fanstatic/tests/ftesting.zcml
src/zope/fanstatic/tests/test_bottom.pt
src/zope/fanstatic/tests/test_computeurl.py
src/zope/fanstatic/tests/test_error.pt
src/zope/fanstatic/tests/test_inline_resource.pt
src/zope/fanstatic/tests/test_multiple.pt
src/zope/fanstatic/tests/test_single.pt
src/zope/fanstatic/tests/tests.py
src/zope/fanstatic/tests/view.py
src/zope/fanstatic/tests/foo_dir/a.js
src/zope/fanstatic/tests/foo_dir/b.js
src/zope/fanstatic/tests/foo_dir/c.js
src/zope/fanstatic/tests/foo_dir/d.js
src/zope/fanstatic/tests/foo_dir/evencaveman.jpg
src/zope/fanstatic/tests/foo_dir/sub/evencaveman.jpg